mcp_ws/__init__.py
mcp_ws/__main__.py
mcp_ws-0.1.6.dist-info/METADATA
mcp_ws-0.1.6.dist-info/WHEEL
mcp_ws-0.1.6.dist-info/entry_points.txt
mcp_ws-0.1.6.dist-info/licenses/LICENSE
mcp_ws-0.1.6.dist-info/RECORD
