Metadata-Version: 2.4
Name: mcp-ws
Version: 0.1.6
Summary: CLI tool to connect local stdio to a remote WebSocket server
License-File: LICENSE
Requires-Python: >=3.12
Requires-Dist: websockets>=13.0
